{
  "assetsByChunkName": {
    "vendors~app-account~app-confirmation~app-order": "chunk.406936ce3c4e9c4e49bd.js",
    "vendors~app-account~app-checkout": "chunk.9783861b427bf3580174.js",
    "vendors~app-cart~app-checkout": "chunk.629243e0e1aee4f6968e.js",
    "admin": [
      "admin.e480627f4ee5dbd62d7e.js",
      "admin.e480627f4ee5dbd62d7e.js.map"
    ],
    "app-account": "chunk.0caec90647193c61b3f7.js",
    "app-checkout": "chunk.70ee4b01a80ddb7e835b.js",
    "app-confirmation": "chunk.17e0dae1d71c20ab8601.js",
    "checkout": [
      "checkout.3a63d4791ab5a0636dcb.js",
      "checkout.3a63d4791ab5a0636dcb.js.map"
    ],
    "storefront": [
      "storefront.d73fcb5c120956fc2bb1.css",
      "storefront.31fcb768e1d9082d2805.js",
      "storefront.d73fcb5c120956fc2bb1.css.map",
      "storefront.31fcb768e1d9082d2805.js.map"
    ],
    "vendors~app-cart": "chunk.d2b4adec85a0a3e4c24b.js",
    "vendors~app-order": "chunk.6ab19b89b9af2a3237ee.js"
  }
}