{
  "meta_title": "VaporStore -  Os melhores aparelhos!",
  "meta_description": "",
  "sections": [
    {
      "type": "banners-grid",
      "banners": [
        {
          "img": "/img/uploads/banner_2024_reabertura.jpg"
        }
      ]
    },
    {
      "type": "collection-shelf",
      "shuffle": true,
      "limit": 4,
      "page": 1,
      "collection_id": "6012679ad6981740b49baa9e:categories:Aparelhos:/vaporizadores/",
      "sort": "sales"
    },
    {
      "type": "collection-shelf",
      "shuffle": true,
      "limit": 4,
      "page": 2,
      "collection_id": "6012679ad6981740b49baa9e:categories:Aparelhos:/vaporizadores/",
      "sort": "sales"
    },
    {
      "type": "collection-shelf",
      "shuffle": true,
      "limit": 4,
      "page": 1,
      "collection_id": "6012679ad6981740b49baa9e:categories:Aparelhos:/vaporizadores/",
      "sort": "sales"
    }
  ]
}